README.md
setup.py
feishupy/__init__.py
feishupy/error_code.py
feishupy/feishu_client.py
feishupy/http_client.py
feishupy.egg-info/PKG-INFO
feishupy.egg-info/SOURCES.txt
feishupy.egg-info/dependency_links.txt
feishupy.egg-info/requires.txt
feishupy.egg-info/top_level.txt
feishupy/api/__init__.py
feishupy/api/authen.py
feishupy/api/base.py
feishupy/api/contact.py
feishupy/api/hook_bot.py
feishupy/api/mina.py
feishupy/session/__init__.py
feishupy/session/memory_storage.py
feishupy/session/redis_storage.py
feishupy/session/session_storage.py
feishupy/session/shove_storage.py