Metadata-Version: 1.1
Name: feishupy
Version: 1.1.14
Summary: A package for FeiShu, Implement API.
Home-page: https://github.com/WUWUTech/feishupy
Author: WUWUTech
Author-email: wuwu@wuwu.tech
License: UNKNOWN
Keywords: feishupy,feishu,SDK
Platform: UNKNOWN
Classifier: Environment :: Console
Classifier: Operating System :: MacOS :: MacOS X
Classifier: Operating System :: Microsoft :: Windows
Classifier: Operating System :: POSIX
Classifier: Programming Language :: Python
Classifier: Programming Language :: Python :: 3.5
Classifier: Programming Language :: Python :: 3.6
Classifier: Programming Language :: Python :: 3.7
